mattermostdriver/__init__.py
mattermostdriver/client.py
mattermostdriver/driver.py
mattermostdriver/exceptions.py
mattermostdriver/version.py
mattermostdriver/websocket.py
mattermostdriver/endpoints/__init__.py
mattermostdriver/endpoints/base.py
mattermostdriver/endpoints/bots.py
mattermostdriver/endpoints/brand.py
mattermostdriver/endpoints/channels.py
mattermostdriver/endpoints/cluster.py
mattermostdriver/endpoints/commands.py
mattermostdriver/endpoints/compliance.py
mattermostdriver/endpoints/data_retention.py
mattermostdriver/endpoints/elasticsearch.py
mattermostdriver/endpoints/emoji.py
mattermostdriver/endpoints/files.py
mattermostdriver/endpoints/integration_actions.py
mattermostdriver/endpoints/ldap.py
mattermostdriver/endpoints/oauth.py
mattermostdriver/endpoints/opengraph.py
mattermostdriver/endpoints/posts.py
mattermostdriver/endpoints/preferences.py
mattermostdriver/endpoints/reactions.py
mattermostdriver/endpoints/roles.py
mattermostdriver/endpoints/saml.py
mattermostdriver/endpoints/scheme.py
mattermostdriver/endpoints/status.py
mattermostdriver/endpoints/system.py
mattermostdriver/endpoints/teams.py
mattermostdriver/endpoints/users.py
mattermostdriver/endpoints/webhooks.py
nordmattermostdriver-7.3.3.dist-info/licenses/LICENSE
nordmattermostdriver-7.3.3.dist-info/METADATA
nordmattermostdriver-7.3.3.dist-info/WHEEL
nordmattermostdriver-7.3.3.dist-info/top_level.txt
nordmattermostdriver-7.3.3.dist-info/RECORD
