Metadata-Version: 2.4
Name: nordmattermostdriver
Version: 7.3.3
Summary: A Python Mattermost Driver
Home-page: https://github.com/i-mantuliak/python-mattermost-driver
Author: Igor Mantuliak
Author-email: igor.mantuliak@my.games
License: MIT
Classifier: Development Status :: 5 - Production/Stable
Classifier: Environment :: Web Environment
Classifier: Intended Audience :: Developers
Classifier: Programming Language :: Python
Classifier: Programming Language :: Python :: 3
Classifier: Programming Language :: Python :: 3.6
Classifier: Programming Language :: Python :: 3.7
Classifier: Programming Language :: Python :: 3.8
Classifier: Programming Language :: Python :: 3.9
Classifier: Programming Language :: Python :: 3.10
Requires-Python: >=3.6
License-File: LICENSE
Requires-Dist: aiohttp<4.0.0,>=3.8.1
Requires-Dist: httpx<0.28.0,>=0.20.0
Dynamic: author
Dynamic: author-email
Dynamic: classifier
Dynamic: description
Dynamic: home-page
Dynamic: license
Dynamic: license-file
Dynamic: requires-dist
Dynamic: requires-python
Dynamic: summary
